roam_mcp/__init__.py
roam_mcp/api.py
roam_mcp/cli.py
roam_mcp/content.py
roam_mcp/content_parsers.py
roam_mcp/memory.py
roam_mcp/search.py
roam_mcp/server.py
roam_mcp/utils.py
iflow_mcp_roam_mcp-0.2.0.dist-info/METADATA
iflow_mcp_roam_mcp-0.2.0.dist-info/WHEEL
iflow_mcp_roam_mcp-0.2.0.dist-info/entry_points.txt
iflow_mcp_roam_mcp-0.2.0.dist-info/licenses/LICENSE
iflow_mcp_roam_mcp-0.2.0.dist-info/RECORD
