Metadata-Version: 2.4
Name: iflow-mcp_roam-mcp
Version: 0.2.0
Summary: A Model Context Protocol server for Roam Research integration with AI assistants
Project-URL: Homepage, https://github.com/PhiloSolares/roam-mcp
Project-URL: Bug Tracker, https://github.com/PhiloSolares/roam-mcp/issues
Author: Roam MCP Project Contributors
License: MIT
License-File: LICENSE
Classifier: Development Status :: 4 - Beta
Classifier: Intended Audience :: End Users/Desktop
Classifier: License :: OSI Approved :: MIT License
Classifier: Programming Language :: Python :: 3
Classifier: Programming Language :: Python :: 3.9
Classifier: Programming Language :: Python :: 3.10
Classifier: Programming Language :: Python :: 3.11
Requires-Python: >=3.9
Requires-Dist: httpx>=0.24.0
Requires-Dist: mcp>=1.3.0
Requires-Dist: pydantic>=2.0.0
Requires-Dist: python-dotenv>=1.0.0
Requires-Dist: requests>=2.28.0
Requires-Dist: trafilatura>=1.6.0
Requires-Dist: unstructured[pdf]>=0.10.0
Requires-Dist: youtube-transcript-api>=0.6.0
Provides-Extra: dev
Requires-Dist: black>=23.0.0; extra == 'dev'
Requires-Dist: isort>=5.12.0; extra == 'dev'
Requires-Dist: mypy>=1.0.0; extra == 'dev'
Requires-Dist: pylint>=2.17.0; extra == 'dev'
Requires-Dist: pytest>=7.0.0; extra == 'dev'
Provides-Extra: pdf
Requires-Dist: poppler-utils>=23.01.0; extra == 'pdf'
